fvm/__init__.py
fvm/run.py
fvm-0.1.2.dist-info/entry_points.txt
fvm-0.1.2.dist-info/WHEEL
fvm-0.1.2.dist-info/METADATA
fvm-0.1.2.dist-info/RECORD
