Metadata-Version: 2.1
Name: fvm
Version: 0.1.2
Summary: Feather Virtual Machine (FVM)
Author-email: $wryl <wryl@wryl.tech>
Maintainer-email: "Justin \"Boonie Pepper\" Hill" <justin@so.dang.cool>
Project-URL: source, https://gitlab.com/feather-lang/fvm
